pyramid_services_autowire/__init__.py
pyramid_services_autowire-0.1.1.dist-info/METADATA
pyramid_services_autowire-0.1.1.dist-info/RECORD
pyramid_services_autowire-0.1.1.dist-info/WHEEL
pyramid_services_autowire-0.1.1.dist-info/top_level.txt
