Metadata-Version: 2.1
Name: pyramid-services-autowire
Version: 0.1.1
Summary: An autowire utility for pyramid_services
Home-page: https://github.com/gjo/pyramid_services_autowire
Author: OCHIAI, Gouji
Author-email: gjo.ext@gmail.com
License: MIT
Platform: UNKNOWN
Classifier: Development Status :: 3 - Alpha
Classifier: Intended Audience :: Developers
Classifier: License :: OSI Approved :: MIT License
Classifier: Programming Language :: Python :: 2
Classifier: Programming Language :: Python :: 2.7
Classifier: Programming Language :: Python :: 3
Classifier: Programming Language :: Python :: 3.4
Classifier: Programming Language :: Python :: 3.5
Classifier: Programming Language :: Python :: 3.6
Provides-Extra: testing
Provides-Extra: develop
Requires-Dist: pyramid
Requires-Dist: pyramid-services
Requires-Dist: zope.interface
Provides-Extra: develop
Requires-Dist: tox; extra == 'develop'
Requires-Dist: twine; extra == 'develop'
Provides-Extra: testing
